{"boxes": [{"position": [590, 295, 335], "size": [295, 295, 75], "color": [19, 82, 214]}, {"position": [0, 295, 225], "size": [295, 295, 70], "color": [213, 168, 49]}, {"position": [0, 0, 388], "size": [295, 295, 70], "color": [169, 113, 43]}, {"position": [590, 0, 75], "size": [295, 295, 75], "color": [224, 48, 144]}, {"position": [295, 295, 145], "size": [295, 295, 70], "color": [168, 76, 52]}, {"position": [295, 0, 0], "size": [295, 295, 75], "color": [164, 22, 6]}, {"position": [0, 295, 295], "size": [295, 295, 75], "color": [213, 90, 81]}, {"position": [590, 0, 195], "size": [295, 295, 75], "color": [221, 37, 114]}, {"position": [0, 0, 460], "size": [295, 295, 55], "color": [67, 9, 53]}, {"position": [0, 295, 510], "size": [295, 295, 75], "color": [74, 147, 208]}, {"position": [295, 0, 388], "size": [295, 295, 60], "color": [177, 110, 183]}, {"position": [590, 295, 0], "size": [295, 295, 75], "color": [236, 138, 120]}, {"position": [295, 295, 516], "size": [295, 295, 69], "color": [230, 20, 173]}, {"position": [0, 0, 235], "size": [295, 295, 80], "color": [133, 127, 110]}, {"position": [590, 295, 225], "size": [295, 295, 50], "color": [180, 232, 41]}, {"position": [590, 0, 0], "size": [295, 295, 70], "color": [55, 104, 103]}, {"position": [295, 295, 215], "size": [295, 295, 70], "color": [165, 27, 8]}, {"position": [0, 295, 440], "size": [295, 295, 70], "color": [98, 63, 118]}, {"position": [590, 0, 460], "size": [295, 295, 40], "color": [24, 178, 137]}, {"position": [295, 0, 225], "size": [295, 295, 55], "color": [9, 70, 168]}, {"position": [590, 295, 275], "size": [295, 295, 60], "color": [38, 197, 146]}, {"position": [590, 0, 500], "size": [295, 295, 85], "color": [119, 182, 197]}, {"position": [0, 295, 70], "size": [295, 295, 75], "color": [83, 157, 80]}, {"position": [0, 295, 145], "size": [295, 295, 80], "color": [41, 162, 229]}, {"position": [0, 0, 515], "size": [295, 295, 70], "color": [47, 187, 109]}, {"position": [295, 0, 448], "size": [295, 295, 70], "color": [233, 84, 48]}, {"position": [590, 295, 150], "size": [295, 295, 75], "color": [64, 29, 79]}, {"position": [0, 295, 0], "size": [295, 295, 70], "color": [40, 19, 32]}, {"position": [590, 0, 270], "size": [295, 295, 70], "color": [143, 108, 14]}, {"position": [590, 0, 150], "size": [295, 295, 45], "color": [47, 3, 112]}, {"position": [295, 295, 356], "size": [295, 295, 100], "color": [217, 166, 175]}, {"position": [0, 0, 180], "size": [295, 295, 55], "color": [178, 206, 130]}, {"position": [295, 0, 328], "size": [295, 295, 60], "color": [162, 111, 63]}, {"position": [590, 295, 410], "size": [295, 295, 100], "color": [109, 76, 115]}, {"position": [295, 0, 518], "size": [295, 295, 60], "color": [188, 164, 169]}, {"position": [295, 295, 456], "size": [295, 295, 60], "color": [24, 171, 33]}, {"position": [590, 295, 75], "size": [295, 295, 75], "color": [49, 201, 88]}, {"position": [0, 0, 35], "size": [295, 295, 145], "color": [123, 240, 148]}, {"position": [590, 295, 510], "size": [295, 295, 75], "color": [247, 207, 89]}, {"position": [295, 295, 75], "size": [295, 295, 70], "color": [249, 228, 219]}, {"position": [590, 0, 340], "size": [295, 295, 60], "color": [204, 117, 179]}, {"position": [295, 295, 285], "size": [295, 295, 70], "color": [15, 4, 190]}, {"position": [590, 0, 400], "size": [295, 295, 60], "color": [210, 72, 177]}, {"position": [295, 295, 0], "size": [295, 295, 75], "color": [128, 158, 69]}, {"position": [295, 0, 280], "size": [295, 295, 48], "color": [79, 25, 83]}, {"position": [295, 0, 75], "size": [295, 295, 75], "color": [8, 86, 52]}, {"position": [0, 0, 315], "size": [295, 295, 68], "color": [213, 78, 142]}, {"position": [0, 0, 0], "size": [295, 295, 35], "color": [210, 5, 47]}, {"position": [0, 295, 370], "size": [295, 295, 70], "color": [18, 135, 225]}, {"position": [295, 0, 150], "size": [295, 295, 75], "color": [199, 43, 85]}], "text": "Solution"}